LICENSE.txt
MANIFEST.in
README.md
pyproject.toml
setup.cfg
src/medver_pytest/__init__.py
src/medver_pytest/build_info.py
src/medver_pytest/cfg.py
src/medver_pytest/cli.py
src/medver_pytest/constants.py
src/medver_pytest/constants_version.py
src/medver_pytest/harness.py
src/medver_pytest/os_specific.py
src/medver_pytest/protocol.py
src/medver_pytest/requirements.py
src/medver_pytest/result_formatter.py
src/medver_pytest/result_summary.py
src/medver_pytest/services.py
src/medver_pytest/status_info.py
src/medver_pytest/stdout_logger.py
src/medver_pytest/summary.py
src/medver_pytest/trace_matrix.py
src/medver_pytest/utils.py
src/medver_pytest/verifier.py
src/medver_pytest.egg-info/PKG-INFO
src/medver_pytest.egg-info/SOURCES.txt
src/medver_pytest.egg-info/dependency_links.txt
src/medver_pytest.egg-info/requires.txt
src/medver_pytest.egg-info/top_level.txt
src/medver_pytest/iuv/__init__.py
src/medver_pytest/iuv/iuv.py
src/medver_pytest/iuv/iuv_data.py
src/medver_pytest/iuv/iuv_requirements.py
src/medver_pytest/log/__init__.py
src/medver_pytest/log/logger.py
src/medver_pytest/log/logger_stdout.py
src/medver_pytest/report/__init__.py
src/medver_pytest/report/report.py
src/medver_pytest/report/common/__init__.py
src/medver_pytest/report/common/footer.py
src/medver_pytest/report/common/gen_base_docx.py
src/medver_pytest/report/common/gen_base_minhtml.py
src/medver_pytest/report/common/gen_base_pdf.py
src/medver_pytest/report/common/gen_base_txt.py
src/medver_pytest/report/common/header.py
src/medver_pytest/report/common/page_details.py
src/medver_pytest/report/common/page_info.py
src/medver_pytest/report/protocol/__init__.py
src/medver_pytest/report/protocol/gen_tp_base.py
src/medver_pytest/report/protocol/gen_tp_docx.py
src/medver_pytest/report/protocol/gen_tp_minhtml.py
src/medver_pytest/report/protocol/gen_tp_pdf.py
src/medver_pytest/report/protocol/gen_tp_txt.py
src/medver_pytest/report/summary/__init__.py
src/medver_pytest/report/summary/gen_summary_base.py
src/medver_pytest/report/summary/gen_summary_docx.py
src/medver_pytest/report/summary/gen_summary_minhtml.py
src/medver_pytest/report/summary/gen_summary_pdf.py
src/medver_pytest/report/summary/gen_summary_txt.py
