Metadata-Version: 2.4
Name: medver-pytest
Version: 1.1.3
Summary: Pytest module with Verification Protocol, Verification Report and Trace Matrix
Author-email: "J. Arrizza" <cppgent0@gmail.com>
Maintainer-email: "J. Arrizza" <cppgent0@gmail.com>
License-Expression: MIT
Project-URL: Website, https://arrizza.com/medver-pytest
Project-URL: Source, https://bitbucket.org/arrizza-public/medver-pytest/src/master
Project-URL: Download, https://bitbucket.org/arrizza-public/medver-pytest/get/master.zip
Keywords: verification,pytest
Classifier: Development Status :: 4 - Beta
Classifier: Framework :: Pytest
Classifier: Topic :: Software Development :: Testing :: Acceptance
Classifier: Intended Audience :: Developers
Classifier: Programming Language :: Python :: 3.10
Classifier: Programming Language :: Python :: 3.12
Requires-Python: >=3.9
License-File: LICENSE.txt
Requires-Dist: docx
Requires-Dist: jsmin
Requires-Dist: pytest
Requires-Dist: pytest-check
Requires-Dist: python-docx
Requires-Dist: reportlab
Requires-Dist: falcon-logger
Dynamic: license-file
